klefki/__init__.py
klefki/algorithms.py
klefki/const.py
klefki/structure.py
klefki/utils.py
klefki/algebra/__init__.py
klefki/algebra/abstract.py
klefki/algebra/concrete.py
klefki/algebra/isomorphism.py
klefki/algebra/meta.py
klefki/algebra/rings.py
klefki/algebra/utils.py
klefki/algebra/fields/__init__.py
klefki/algebra/fields/polyfield.py
klefki/algebra/fields/primefield.py
klefki/algebra/groups/__init__.py
klefki/algebra/groups/cycic_group.py
klefki/algebra/groups/cyclic_group.py
klefki/algebra/groups/ecg.py
klefki/algebra/groups/jacobian.py
klefki/algebra/groups/ecg/__init__.py
klefki/algebra/groups/ecg/elliptic.py
klefki/asn/__init__.py
klefki/asn/signature.py
klefki/blockchain/__init__.py
klefki/blockchain/bitcoin/__init__.py
klefki/blockchain/bitcoin/address.py
klefki/blockchain/bitcoin/const.py
klefki/blockchain/bitcoin/private.py
klefki/blockchain/bitcoin/public.py
klefki/blockchain/bitcoin/sign.py
klefki/blockchain/bitcoin/asn/__init__.py
klefki/blockchain/bitcoin/asn/signature.py
klefki/blockchain/eos/__init__.py
klefki/blockchain/eos/address.py
klefki/blockchain/eos/private.py
klefki/blockchain/eos/public.py
klefki/blockchain/ethereum/__init__.py
klefki/blockchain/ethereum/address.py
klefki/blockchain/ethereum/private.py
klefki/blockchain/ethereum/public.py
klefki/client/__init__.py
klefki/client/shell.py
klefki/crypto/MiMC.py
klefki/crypto/__init__.py
klefki/crypto/damgard_jurik.py
klefki/crypto/elgamal.py
klefki/crypto/paillier.py
klefki/crypto/pkcs.py
klefki/crypto/rsa.py
klefki/crypto/sponge.py
klefki/crypto/ssss.py
klefki/crypto/vss.py
klefki/crypto/ecdsa/__init__.py
klefki/crypto/ecdsa/secp256k1.py
klefki/crypto/ecdsa/secp256r1.py
klefki/curves/__init__.py
klefki/curves/arith.py
klefki/curves/baby_jubjub.py
klefki/curves/secp256k1.py
klefki/curves/barreto_naehrig/__init__.py
klefki/curves/barreto_naehrig/bn128.py
klefki/curves/barreto_naehrig/bn254.py
klefki/mpc/__init__.py
klefki/mpc/secret_sharing.py
klefki/numbers/__init__.py
klefki-1.7.1.dist-info/LICENSE
klefki-1.7.1.dist-info/METADATA
klefki-1.7.1.dist-info/WHEEL
klefki-1.7.1.dist-info/entry_points.txt
klefki-1.7.1.dist-info/top_level.txt
klefki-1.7.1.dist-info/RECORD
