Metadata-Version: 2.1
Name: klefki
Version: 1.7.1
Summary: Klefki is a playground for researching elliptic curve group based algorithms & applications, such as MPC, HE, ZKP, and Bitcoin/Ethereum. All data types & structures are based on mathematical defination of abstract algebra.
Home-page: https://github.com/ZeroProphet/klefki
Author: Ryan Kung
Author-email: ryankung@ieee.org
License: GPL
Platform: UNKNOWN
Classifier: Development Status :: 5 - Production/Stable
Classifier: Environment :: Console
Classifier: Programming Language :: Python :: 3.5
Classifier: Programming Language :: Python :: Implementation :: CPython
Classifier: Programming Language :: Python :: Implementation :: PyPy
Classifier: Operating System :: OS Independent
Classifier: Topic :: Software Development
Classifier: Topic :: Software Development :: Libraries :: Python Modules
Classifier: Topic :: Security :: Cryptography
Requires-Dist: pyasn1 (==0.3.7)
Requires-Dist: base58 (==0.2.5)
Requires-Dist: asn1ate (==0.6.0)
Requires-Dist: pysha3 (==1.0.2)
Requires-Dist: flatbuffers (==1.12)
